TGIF/TGIF.py
TGIF/__init__.py
TGIF-1.0.5.dist-info/METADATA
TGIF-1.0.5.dist-info/WHEEL
TGIF-1.0.5.dist-info/top_level.txt
TGIF-1.0.5.dist-info/RECORD
