Metadata-Version: 2.1
Name: TGIF
Version: 1.0.5
Requires-Dist: numpy
Requires-Dist: scipy
Requires-Dist: astropy
Requires-Dist: matplotlib
Requires-Dist: pandas
